{
	"bRegularFrameSize" : true,
	"m_eResType" : 4,
	"m_strKey" : "SC/thingy/VSmokeDeplete(geysmok4).bmp",
	"mapAnim" : 
	{
		"VESPENE_SMOKE_1_DEPLETE" : 
		{
			"eAnimType" : 0,
			"fFullPlayTime" : 1065353216,
			"uColTotal" : 0,
			"uNumFrame" : 8,
			"uRowTotal" : 0,
			"vPivot" : 4539628425446424576,
			"vecFrame" : 
			[
				0,
				1,
				2,
				3,
				4,
				5,
				6,
				7
			]
		}
	},
	"strKeyAtlasTex" : "SC/thingy/VSmokeDeplete(geysmok4).bmp",
	"vecFrameUV" : 
	{
		"v2_Offset" : 
		[
			0,
			0,
			0,
			0,
			0,
			0,
			0,
			0
		],
		"v2_UVLeftTop" : 
		[
			0,
			1040187392,
			1048576000,
			1052770304,
			1056964608,
			1059061760,
			1061158912,
			1063256064
		],
		"v2_UVSlice" : 
		[
			4575657222448611328,
			4575657222448611328,
			4575657222448611328,
			4575657222448611328,
			4575657222448611328,
			4575657222448611328,
			4575657222448611328,
			4575657222448611328
		]
	}
}